pythonic_fp/sentinels/__init__.py
pythonic_fp/sentinels/__init__.pyi
pythonic_fp/sentinels/flavored.py
pythonic_fp/sentinels/flavored.pyi
pythonic_fp/sentinels/novalue.py
pythonic_fp/sentinels/novalue.pyi
pythonic_fp/sentinels/py.typed
pythonic_fp_sentinels-2.1.3.dist-info/licenses/LICENSE
pythonic_fp_sentinels-2.1.3.dist-info/WHEEL
pythonic_fp_sentinels-2.1.3.dist-info/METADATA
pythonic_fp_sentinels-2.1.3.dist-info/RECORD
