Metadata-Version: 2.4
Name: pythonic-fp-sentinels
Version: 2.1.3
Summary: Sentinels
Keywords: sentinel,singleton
Author-email: "Geoffrey R. Scheller" <geoffrey@scheller.com>
Requires-Python: >=3.13
Classifier: Development Status :: 7 - Inactive
Classifier: Framework :: Pytest
Classifier: Intended Audience :: Developers
Classifier: License :: OSI Approved :: Apache Software License
Classifier: Operating System :: OS Independent
Classifier: Programming Language :: Python :: 3.13
Classifier: Typing :: Typed
License-File: LICENSE
Requires-Dist: pytest>=8.4.1 ; extra == "test"
Project-URL: Changelog, https://github.com/grscheller/pythonic-fp-sentinels/blob/main/CHANGELOG.rst
Project-URL: Documentation, https://grscheller.github.io/pythonic-fp/sentinels/v2.1.3/build/html/index.html
Project-URL: Homepage, https://github.com/grscheller/pythonic-fp/blob/main/README.md
Project-URL: Source, https://github.com/grscheller/pythonic-fp-sentinels
Provides-Extra: test
